{
  "cpma": [
    {
      "applicable": true,
      "rating": "0.6666",
      "localteam_id": "365577bb-31c6-46fb-8e42-9e3e53376cf0",
      "measure_id": "49ad949c-3984-4054-9260-11fc05301088",
      "id": "13c62682-30f7-4908-9138-bd1b36b01438",
      "source": "sadf",
      "current_progress": "asdf",
      "date_updated": "2025-09-19T10:12:36.621Z",
      "why_not_applicable": null,
      "status": "published",
      "measure_published": true,
      "measure": {
        "id": "49ad949c-3984-4054-9260-11fc05301088",
        "name": "k8",
        "sector": "cpma",
        "slug": "k8",
        "impact": 3,
        "weight": 3,
        "feasibility_political": "2",
        "feasibility_economical": "3",
        "verification_description": null,
        "notes": null,
        "description": null,
        "date_updated": "2025-09-19T10:01:56.620Z",
        "description_evaluation_criteria": "<p>wadsv</p>",
        "description_about": "<p>wrefdsv</p>",
        "description_benefit": null,
        "description_verification": "<p>asdfva</p>",
        "description_contribution": null,
        "description_implementation": null,
        "description_legal": null,
        "description_funding": null,
        "description_tutorial": null,
        "measure_id": "k8"
      }
    },
    {
      "applicable": true,
      "rating": "0.6666",
      "localteam_id": "365577bb-31c6-46fb-8e42-9e3e53376cf0",
      "measure_id": "669312f6-3654-4d4b-9de0-69b0923add61",
      "id": "3a48ccf6-75b3-4ea8-a58a-e8bc52322326",
      "source": "sadf",
      "current_progress": "asdf",
      "date_updated": "2025-09-19T10:12:36.664Z",
      "why_not_applicable": null,
      "status": "published",
      "measure_published": true,
      "measure": {
        "id": "669312f6-3654-4d4b-9de0-69b0923add61",
        "name": "Klima2",
        "sector": "cpma",
        "slug": "klima2",
        "impact": 3,
        "weight": 2,
        "feasibility_political": "4",
        "feasibility_economical": "4",
        "verification_description": null,
        "notes": null,
        "description": null,
        "date_updated": "2025-09-19T10:01:56.592Z",
        "description_evaluation_criteria": "<p>&ouml;alksdjf</p>",
        "description_about": "<p>erkj</p>",
        "description_benefit": null,
        "description_verification": "<p>lksajfd</p>",
        "description_contribution": null,
        "description_implementation": null,
        "description_legal": null,
        "description_funding": null,
        "description_tutorial": null,
        "measure_id": "kl2"
      }
    },
    {
      "applicable": true,
      "rating": "0.6666",
      "localteam_id": "365577bb-31c6-46fb-8e42-9e3e53376cf0",
      "measure_id": "8375a9b5-7dac-4fd9-8265-af97d7b300d6",
      "id": "42b100c7-ead5-4499-9a16-a50e2e3f3f96",
      "source": "sadf",
      "current_progress": "asdf",
      "date_updated": "2025-09-19T10:12:36.688Z",
      "why_not_applicable": null,
      "status": "published",
      "measure_published": true,
      "measure": {
        "id": "8375a9b5-7dac-4fd9-8265-af97d7b300d6",
        "name": "k5",
        "sector": "cpma",
        "slug": "k5",
        "impact": 3,
        "weight": 1,
        "feasibility_political": "2",
        "feasibility_economical": "4",
        "verification_description": null,
        "notes": null,
        "description": null,
        "date_updated": "2025-09-19T10:01:56.627Z",
        "description_evaluation_criteria": "<p>asdf</p>",
        "description_about": "<p>df</p>",
        "description_benefit": null,
        "description_verification": "<p>sadf</p>",
        "description_contribution": null,
        "description_implementation": null,
        "description_legal": null,
        "description_funding": null,
        "description_tutorial": null,
        "measure_id": "k5"
      }
    },
    {
      "applicable": true,
      "rating": "0.6666",
      "localteam_id": "365577bb-31c6-46fb-8e42-9e3e53376cf0",
      "measure_id": "1182ca63-d297-4a6e-8ddd-283b49038777",
      "id": "648b1a87-8087-4693-866c-0850d0d7e4df",
      "source": "sadf",
      "current_progress": "asdf",
      "date_updated": "2025-09-19T10:12:36.786Z",
      "why_not_applicable": null,
      "status": "published",
      "measure_published": true,
      "measure": {
        "id": "1182ca63-d297-4a6e-8ddd-283b49038777",
        "name": "k7",
        "sector": "cpma",
        "slug": "k7",
        "impact": 5,
        "weight": 2,
        "feasibility_political": "5",
        "feasibility_economical": "3",
        "verification_description": null,
        "notes": null,
        "description": null,
        "date_updated": "2025-09-19T10:01:56.596Z",
        "description_evaluation_criteria": "<p>qwer</p>",
        "description_about": "<p>qwer</p>",
        "description_benefit": null,
        "description_verification": "<p>wqer</p>",
        "description_contribution": null,
        "description_implementation": null,
        "description_legal": null,
        "description_funding": null,
        "description_tutorial": null,
        "measure_id": "k7"
      }
    },
    {
      "applicable": true,
      "rating": "0.6666",
      "localteam_id": "365577bb-31c6-46fb-8e42-9e3e53376cf0",
      "measure_id": "49e280b3-20b9-48cb-97a7-bb9043d228f4",
      "id": "8ee73b32-cc88-4179-83b2-a7971a3e8a67",
      "source": "sadf",
      "current_progress": "asdf",
      "date_updated": "2025-09-19T10:12:36.839Z",
      "why_not_applicable": null,
      "status": "published",
      "measure_published": true,
      "measure": {
        "id": "49e280b3-20b9-48cb-97a7-bb9043d228f4",
        "name": "klima3",
        "sector": "cpma",
        "slug": "klima3",
        "impact": 1,
        "weight": 3,
        "feasibility_political": "2",
        "feasibility_economical": "3",
        "verification_description": null,
        "notes": null,
        "description": null,
        "date_updated": "2025-09-19T10:01:56.591Z",
        "description_evaluation_criteria": "<p>Land 2</p>",
        "description_about": "<p>asdf</p>",
        "description_benefit": null,
        "description_verification": "<p>Land 2</p>",
        "description_contribution": null,
        "description_implementation": null,
        "description_legal": null,
        "description_funding": null,
        "description_tutorial": null,
        "measure_id": "kl3"
      }
    },
    {
      "applicable": true,
      "rating": "0.6666",
      "localteam_id": "365577bb-31c6-46fb-8e42-9e3e53376cf0",
      "measure_id": "25aaff35-5227-4c2e-8a28-571db47364bb",
      "id": "b8d5e928-7e8e-40fb-a99c-1d24618ff0af",
      "source": "sadf",
      "current_progress": "asdf",
      "date_updated": "2025-09-19T10:12:36.859Z",
      "why_not_applicable": null,
      "status": "published",
      "measure_published": true,
      "measure": {
        "id": "25aaff35-5227-4c2e-8a28-571db47364bb",
        "name": "Mb5",
        "sector": "cpma",
        "slug": "mb5",
        "impact": 4,
        "weight": 2,
        "feasibility_political": "1",
        "feasibility_economical": "1",
        "verification_description": null,
        "notes": null,
        "description": null,
        "date_updated": "2025-09-19T10:01:56.620Z",
        "description_evaluation_criteria": "<p>asdf</p>",
        "description_about": "<p>asdf</p>",
        "description_benefit": null,
        "description_verification": "<p>asdf</p>",
        "description_contribution": null,
        "description_implementation": null,
        "description_legal": null,
        "description_funding": null,
        "description_tutorial": null,
        "measure_id": "EN_5"
      }
    },
    {
      "applicable": true,
      "rating": "0.6666",
      "localteam_id": "365577bb-31c6-46fb-8e42-9e3e53376cf0",
      "measure_id": "ac5fcccd-24ef-43f8-965f-5b462bd218f1",
      "id": "db26381c-5618-4a29-bd36-e22964575dc7",
      "source": "sadf",
      "current_progress": "asdf",
      "date_updated": "2025-09-19T10:12:36.895Z",
      "why_not_applicable": null,
      "status": "published",
      "measure_published": true,
      "measure": {
        "id": "ac5fcccd-24ef-43f8-965f-5b462bd218f1",
        "name": "k6",
        "sector": "cpma",
        "slug": "k6",
        "impact": 2,
        "weight": 3,
        "feasibility_political": "3",
        "feasibility_economical": "3",
        "verification_description": null,
        "notes": null,
        "description": null,
        "date_updated": "2025-09-19T10:01:56.625Z",
        "description_evaluation_criteria": "<p>sadf</p>",
        "description_about": "<p>asdf</p>",
        "description_benefit": null,
        "description_verification": "<p>sdf</p>",
        "description_contribution": null,
        "description_implementation": null,
        "description_legal": null,
        "description_funding": null,
        "description_tutorial": null,
        "measure_id": "k6"
      }
    },
    {
      "applicable": true,
      "rating": "0.3333",
      "localteam_id": "365577bb-31c6-46fb-8e42-9e3e53376cf0",
      "measure_id": "931c9f55-47f2-4a6a-b294-c3354ae7c9f9",
      "id": "df443ed5-6f05-4320-82b7-d6848972ec53",
      "source": "sadf",
      "current_progress": "asdf",
      "date_updated": "2025-09-19T10:14:16.348Z",
      "why_not_applicable": null,
      "status": "published",
      "measure_published": true,
      "measure": {
        "id": "931c9f55-47f2-4a6a-b294-c3354ae7c9f9",
        "name": "k4",
        "sector": "cpma",
        "slug": "k4",
        "impact": 2,
        "weight": 2,
        "feasibility_political": "2",
        "feasibility_economical": "3",
        "verification_description": null,
        "notes": null,
        "description": null,
        "date_updated": "2025-09-19T10:01:56.589Z",
        "description_evaluation_criteria": "<p>df</p>",
        "description_about": "<p>adgf</p>",
        "description_benefit": null,
        "description_verification": "<p>&auml;p&ouml;</p>",
        "description_contribution": null,
        "description_implementation": null,
        "description_legal": null,
        "description_funding": null,
        "description_tutorial": null,
        "measure_id": "k4"
      }
    }
  ],
  "bh": [
    {
      "applicable": true,
      "rating": "0",
      "localteam_id": "365577bb-31c6-46fb-8e42-9e3e53376cf0",
      "measure_id": "628f245c-3f0f-45f7-afa8-361ad1a68251",
      "id": "1b14fb82-a44d-4f46-82b0-c05b0fa87ef3",
      "source": "sadf",
      "current_progress": "asdf",
      "date_updated": "2025-09-19T10:12:48.894Z",
      "why_not_applicable": null,
      "status": "published",
      "measure_published": true,
      "measure": {
        "id": "628f245c-3f0f-45f7-afa8-361ad1a68251",
        "name": "g7",
        "sector": "bh",
        "slug": "g7",
        "impact": 2,
        "weight": 2,
        "feasibility_political": "3",
        "feasibility_economical": "2",
        "verification_description": null,
        "notes": null,
        "description": null,
        "date_updated": "2025-09-19T10:01:56.588Z",
        "description_evaluation_criteria": "<p>asdvc&nbsp;</p>",
        "description_about": "<p>wedsv</p>",
        "description_benefit": null,
        "description_verification": "<p>dsfv</p>",
        "description_contribution": null,
        "description_implementation": null,
        "description_legal": null,
        "description_funding": null,
        "description_tutorial": null,
        "measure_id": "g7"
      }
    },
    {
      "applicable": true,
      "rating": "0.6666",
      "localteam_id": "365577bb-31c6-46fb-8e42-9e3e53376cf0",
      "measure_id": "5c95dd7b-0330-4d19-8ad5-c3baccedfda5",
      "id": "43dea99d-f9a4-4635-943d-ce2b3a7bb4d7",
      "source": "sadf",
      "current_progress": "asdf",
      "date_updated": "2025-09-19T10:12:36.703Z",
      "why_not_applicable": null,
      "status": "published",
      "measure_published": true,
      "measure": {
        "id": "5c95dd7b-0330-4d19-8ad5-c3baccedfda5",
        "name": "g4",
        "sector": "bh",
        "slug": "g4",
        "impact": 3,
        "weight": 3,
        "feasibility_political": "2",
        "feasibility_economical": "2",
        "verification_description": null,
        "notes": null,
        "description": null,
        "date_updated": "2025-09-19T10:01:56.588Z",
        "description_evaluation_criteria": "<p>wer</p>",
        "description_about": "<p>wer</p>",
        "description_benefit": null,
        "description_verification": "<p>qwre</p>",
        "description_contribution": null,
        "description_implementation": null,
        "description_legal": null,
        "description_funding": null,
        "description_tutorial": null,
        "measure_id": "g4"
      }
    },
    {
      "applicable": true,
      "rating": "0.6666",
      "localteam_id": "365577bb-31c6-46fb-8e42-9e3e53376cf0",
      "measure_id": "4568d52f-9ffa-4f60-a234-9b840c8831d3",
      "id": "51d85ae6-d718-44e3-bbb0-0dbea0c5f193",
      "source": "sadf",
      "current_progress": "asdf",
      "date_updated": "2025-09-19T10:12:36.742Z",
      "why_not_applicable": null,
      "status": "published",
      "measure_published": true,
      "measure": {
        "id": "4568d52f-9ffa-4f60-a234-9b840c8831d3",
        "name": "g5",
        "sector": "bh",
        "slug": "g5",
        "impact": 3,
        "weight": 2,
        "feasibility_political": "2",
        "feasibility_economical": "4",
        "verification_description": null,
        "notes": null,
        "description": null,
        "date_updated": "2025-09-19T10:01:56.550Z",
        "description_evaluation_criteria": "<p>asdf</p>",
        "description_about": "<p>asdf</p>",
        "description_benefit": null,
        "description_verification": "<p>sadf</p>",
        "description_contribution": null,
        "description_implementation": null,
        "description_legal": null,
        "description_funding": null,
        "description_tutorial": null,
        "measure_id": "g5"
      }
    },
    {
      "applicable": true,
      "rating": "0.6666",
      "localteam_id": "365577bb-31c6-46fb-8e42-9e3e53376cf0",
      "measure_id": "ecdb9400-7eac-48b4-aeb7-52684a17d8a6",
      "id": "54d1a5fb-bfb1-4356-9072-5f8a98f75edd",
      "source": "sadf",
      "current_progress": "asdf",
      "date_updated": "2025-09-19T10:12:36.748Z",
      "why_not_applicable": null,
      "status": "published",
      "measure_published": true,
      "measure": {
        "id": "ecdb9400-7eac-48b4-aeb7-52684a17d8a6",
        "name": "g6",
        "sector": "bh",
        "slug": "g6",
        "impact": 2,
        "weight": 2,
        "feasibility_political": "3",
        "feasibility_economical": "2",
        "verification_description": null,
        "notes": null,
        "description": null,
        "date_updated": "2025-09-19T10:01:56.587Z",
        "description_evaluation_criteria": "<p>asdf</p>",
        "description_about": "<p>adfs</p>",
        "description_benefit": null,
        "description_verification": "<p>sdf</p>",
        "description_contribution": null,
        "description_implementation": null,
        "description_legal": null,
        "description_funding": null,
        "description_tutorial": null,
        "measure_id": "g6"
      }
    },
    {
      "applicable": true,
      "rating": "0.6666",
      "localteam_id": "365577bb-31c6-46fb-8e42-9e3e53376cf0",
      "measure_id": "743ee205-b139-4b72-b696-4b2b7a3912e8",
      "id": "587695d2-95f2-41e4-bfbe-95634ef746bd",
      "source": "sadf",
      "current_progress": "asdf",
      "date_updated": "2025-09-19T10:12:36.764Z",
      "why_not_applicable": null,
      "status": "published",
      "measure_published": true,
      "measure": {
        "id": "743ee205-b139-4b72-b696-4b2b7a3912e8",
        "name": "Gebäude 2",
        "sector": "bh",
        "slug": "gebaeude-2",
        "impact": 2,
        "weight": 2,
        "feasibility_political": "2",
        "feasibility_economical": "4",
        "verification_description": null,
        "notes": null,
        "description": null,
        "date_updated": "2025-09-19T10:01:56.549Z",
        "description_evaluation_criteria": "<p>qwetz</p>",
        "description_about": "<p>234qref</p>",
        "description_benefit": null,
        "description_verification": "<p>adfg</p>",
        "description_contribution": null,
        "description_implementation": null,
        "description_legal": null,
        "description_funding": null,
        "description_tutorial": null,
        "measure_id": "Gb2"
      }
    },
    {
      "applicable": true,
      "rating": "0.6666",
      "localteam_id": "365577bb-31c6-46fb-8e42-9e3e53376cf0",
      "measure_id": "179b7993-fde4-433c-88f3-e0096d0f52e7",
      "id": "6870f0b2-2e02-462c-a5b4-9ccd46b6538c",
      "source": "sadf",
      "current_progress": "asdf",
      "date_updated": "2025-09-19T10:12:36.792Z",
      "why_not_applicable": null,
      "status": "published",
      "measure_published": true,
      "measure": {
        "id": "179b7993-fde4-433c-88f3-e0096d0f52e7",
        "name": "aset",
        "sector": "bh",
        "slug": "aset",
        "impact": null,
        "weight": 5,
        "feasibility_political": null,
        "feasibility_economical": null,
        "verification_description": null,
        "notes": null,
        "description": null,
        "date_updated": "2025-09-19T09:55:00.449Z",
        "description_evaluation_criteria": "<p>asdf</p>",
        "description_about": "<p>asfd</p>",
        "description_benefit": null,
        "description_verification": "<p>asdf</p>",
        "description_contribution": null,
        "description_implementation": null,
        "description_legal": null,
        "description_funding": null,
        "description_tutorial": null,
        "measure_id": "tset"
      }
    },
    {
      "applicable": true,
      "rating": "0.6666",
      "localteam_id": "365577bb-31c6-46fb-8e42-9e3e53376cf0",
      "measure_id": "5dac9a1c-d114-4499-91fb-80fafad04ce7",
      "id": "6ec75860-7d9e-4cfd-95cc-b1500149a47f",
      "source": "sadf",
      "current_progress": "asdf",
      "date_updated": "2025-09-19T10:12:36.806Z",
      "why_not_applicable": null,
      "status": "published",
      "measure_published": true,
      "measure": {
        "id": "5dac9a1c-d114-4499-91fb-80fafad04ce7",
        "name": "Wärme 3",
        "sector": "bh",
        "slug": "waerme-3",
        "impact": 5,
        "weight": 2,
        "feasibility_political": "2",
        "feasibility_economical": "5",
        "verification_description": null,
        "notes": null,
        "description": null,
        "date_updated": "2025-09-19T10:01:56.550Z",
        "description_evaluation_criteria": "<p>qwer</p>",
        "description_about": "<p>12345</p>",
        "description_benefit": null,
        "description_verification": "<p>ret</p>",
        "description_contribution": null,
        "description_implementation": null,
        "description_legal": null,
        "description_funding": null,
        "description_tutorial": null,
        "measure_id": "Gb3"
      }
    },
    {
      "applicable": true,
      "rating": "0.6666",
      "localteam_id": "365577bb-31c6-46fb-8e42-9e3e53376cf0",
      "measure_id": "d0948fee-e8d9-4167-8053-5a44e13af801",
      "id": "96e702f7-5dab-4220-afa4-e7d6a5fa40ed",
      "source": "sadf",
      "current_progress": "asdf",
      "date_updated": "2025-09-19T10:12:36.845Z",
      "why_not_applicable": null,
      "status": "published",
      "measure_published": true,
      "measure": {
        "id": "d0948fee-e8d9-4167-8053-5a44e13af801",
        "name": "Maßnahme 1",
        "sector": "bh",
        "slug": "massnahme-1",
        "impact": 3,
        "weight": 3,
        "feasibility_political": null,
        "feasibility_economical": null,
        "verification_description": null,
        "notes": null,
        "description": null,
        "date_updated": "2025-09-19T10:01:56.548Z",
        "description_evaluation_criteria": "<p>blllas</p>",
        "description_about": "<p>bak</p>",
        "description_benefit": null,
        "description_verification": "<p>asdf</p>",
        "description_contribution": null,
        "description_implementation": null,
        "description_legal": null,
        "description_funding": null,
        "description_tutorial": null,
        "measure_id": "EN2"
      }
    }
  ],
  "transport": [
    {
      "applicable": true,
      "rating": "0.6666",
      "localteam_id": "365577bb-31c6-46fb-8e42-9e3e53376cf0",
      "measure_id": "2337c72f-df30-4e06-a447-7f657fae24c2",
      "id": "24eb6c73-18e3-4574-a169-a62e840d71a1",
      "source": "sadf",
      "current_progress": "asdf",
      "date_updated": "2025-09-19T10:12:36.639Z",
      "why_not_applicable": null,
      "status": "published",
      "measure_published": true,
      "measure": {
        "id": "2337c72f-df30-4e06-a447-7f657fae24c2",
        "name": "v5",
        "sector": "transport",
        "slug": "v5",
        "impact": 3,
        "weight": 2,
        "feasibility_political": "3",
        "feasibility_economical": "4",
        "verification_description": null,
        "notes": null,
        "description": null,
        "date_updated": "2025-09-19T10:01:56.713Z",
        "description_evaluation_criteria": "<p>qwer</p>",
        "description_about": "<p>35345</p>",
        "description_benefit": null,
        "description_verification": "<p>wqerLand 2</p>",
        "description_contribution": null,
        "description_implementation": null,
        "description_legal": null,
        "description_funding": null,
        "description_tutorial": null,
        "measure_id": "v5"
      }
    },
    {
      "applicable": true,
      "rating": "0.6666",
      "localteam_id": "365577bb-31c6-46fb-8e42-9e3e53376cf0",
      "measure_id": "16538485-67c6-4276-86af-bf8da22af3ca",
      "id": "404e94db-fc2c-443a-afbd-f8a90a23d728",
      "source": "sadf",
      "current_progress": "asdf",
      "date_updated": "2025-09-19T10:12:36.680Z",
      "why_not_applicable": null,
      "status": "published",
      "measure_published": true,
      "measure": {
        "id": "16538485-67c6-4276-86af-bf8da22af3ca",
        "name": "v6",
        "sector": "transport",
        "slug": "v6",
        "impact": 2,
        "weight": 2,
        "feasibility_political": "2",
        "feasibility_economical": "3",
        "verification_description": null,
        "notes": null,
        "description": null,
        "date_updated": "2025-09-19T10:01:56.716Z",
        "description_evaluation_criteria": "<p>Land 2</p>",
        "description_about": "<p>ewr</p>",
        "description_benefit": null,
        "description_verification": "<p>Land 2</p>",
        "description_contribution": null,
        "description_implementation": null,
        "description_legal": null,
        "description_funding": null,
        "description_tutorial": null,
        "measure_id": "v6"
      }
    },
    {
      "applicable": true,
      "rating": "0.6666",
      "localteam_id": "365577bb-31c6-46fb-8e42-9e3e53376cf0",
      "measure_id": "6df1f618-b82b-4e13-9b75-b0e5d34c9aeb",
      "id": "48a33bad-ee08-4d1a-b219-81cde2356023",
      "source": "sadf",
      "current_progress": "asdf",
      "date_updated": "2025-09-19T10:12:36.712Z",
      "why_not_applicable": null,
      "status": "published",
      "measure_published": true,
      "measure": {
        "id": "6df1f618-b82b-4e13-9b75-b0e5d34c9aeb",
        "name": "verkehr2",
        "sector": "transport",
        "slug": "verkehr2",
        "impact": 3,
        "weight": 3,
        "feasibility_political": "3",
        "feasibility_economical": "2",
        "verification_description": null,
        "notes": null,
        "description": null,
        "date_updated": "2025-09-19T10:01:56.716Z",
        "description_evaluation_criteria": "<p>asdf</p>",
        "description_about": "<p>wer</p>",
        "description_benefit": null,
        "description_verification": "<p>asdf</p>",
        "description_contribution": null,
        "description_implementation": null,
        "description_legal": null,
        "description_funding": null,
        "description_tutorial": null,
        "measure_id": "verkehr2"
      }
    },
    {
      "applicable": true,
      "rating": "0.6666",
      "localteam_id": "365577bb-31c6-46fb-8e42-9e3e53376cf0",
      "measure_id": "b75878a9-ede1-4049-ac56-97cf46222367",
      "id": "567f75d5-f4cb-4561-a0e6-3fe870d415d9",
      "source": "sadf",
      "current_progress": "asdf",
      "date_updated": "2025-09-19T10:12:36.757Z",
      "why_not_applicable": null,
      "status": "published",
      "measure_published": true,
      "measure": {
        "id": "b75878a9-ede1-4049-ac56-97cf46222367",
        "name": "verkehr 3",
        "sector": "transport",
        "slug": "verkehr-3",
        "impact": 5,
        "weight": 1,
        "feasibility_political": "3",
        "feasibility_economical": "2",
        "verification_description": null,
        "notes": null,
        "description": null,
        "date_updated": "2025-09-19T10:01:56.681Z",
        "description_evaluation_criteria": "<p>asdf</p>",
        "description_about": "<p>asdf</p>",
        "description_benefit": null,
        "description_verification": "<p>sadf</p>",
        "description_contribution": null,
        "description_implementation": null,
        "description_legal": null,
        "description_funding": null,
        "description_tutorial": null,
        "measure_id": "v3"
      }
    },
    {
      "applicable": true,
      "rating": "0.6666",
      "localteam_id": "365577bb-31c6-46fb-8e42-9e3e53376cf0",
      "measure_id": "efd6a479-71ec-4f84-83bf-fb4ceed2887e",
      "id": "79208918-6867-49b2-bbcf-33a4baa87c16",
      "source": "sadf",
      "current_progress": "asdf",
      "date_updated": "2025-09-19T10:12:36.812Z",
      "why_not_applicable": null,
      "status": "published",
      "measure_published": true,
      "measure": {
        "id": "efd6a479-71ec-4f84-83bf-fb4ceed2887e",
        "name": "EN6",
        "sector": "transport",
        "slug": "en6",
        "impact": 5,
        "weight": 1,
        "feasibility_political": "4",
        "feasibility_economical": "3",
        "verification_description": null,
        "notes": null,
        "description": null,
        "date_updated": "2025-09-19T10:01:56.714Z",
        "description_evaluation_criteria": "<p>wqer</p>",
        "description_about": "<p>asdf</p>",
        "description_benefit": null,
        "description_verification": "<p>wqer</p>",
        "description_contribution": null,
        "description_implementation": null,
        "description_legal": null,
        "description_funding": null,
        "description_tutorial": null,
        "measure_id": "EN6"
      }
    },
    {
      "applicable": true,
      "rating": "0.6666",
      "localteam_id": "365577bb-31c6-46fb-8e42-9e3e53376cf0",
      "measure_id": "c7ee1d16-468e-4ba1-9704-2e17d2a717eb",
      "id": "bcabc5b8-8d34-4e81-b349-cb58bab082b0",
      "source": "sadf",
      "current_progress": "asdf",
      "date_updated": "2025-09-19T10:12:36.872Z",
      "why_not_applicable": null,
      "status": "published",
      "measure_published": true,
      "measure": {
        "id": "c7ee1d16-468e-4ba1-9704-2e17d2a717eb",
        "name": "v4",
        "sector": "transport",
        "slug": "v4",
        "impact": 2,
        "weight": 2,
        "feasibility_political": "2",
        "feasibility_economical": "3",
        "verification_description": null,
        "notes": null,
        "description": null,
        "date_updated": "2025-09-19T10:01:56.683Z",
        "description_evaluation_criteria": "<p>qewr</p>",
        "description_about": "<p>ewr</p>",
        "description_benefit": null,
        "description_verification": "<p>weqr</p>",
        "description_contribution": null,
        "description_implementation": null,
        "description_legal": null,
        "description_funding": null,
        "description_tutorial": null,
        "measure_id": "v4"
      }
    }
  ],
  "energy": [
    {
      "applicable": true,
      "rating": "0",
      "localteam_id": "365577bb-31c6-46fb-8e42-9e3e53376cf0",
      "measure_id": "ad91c6de-5307-41a9-82d5-f9bab510d360",
      "id": "2f189348-8c71-4599-85e4-a7a355450593",
      "source": "sadf",
      "current_progress": "asdf",
      "date_updated": "2025-09-19T10:12:55.144Z",
      "why_not_applicable": null,
      "status": "published",
      "measure_published": true,
      "measure": {
        "id": "ad91c6de-5307-41a9-82d5-f9bab510d360",
        "name": "e6",
        "sector": "energy",
        "slug": "e6",
        "impact": 2,
        "weight": 2,
        "feasibility_political": "1",
        "feasibility_economical": "2",
        "verification_description": null,
        "notes": null,
        "description": null,
        "date_updated": "2025-09-19T10:01:56.627Z",
        "description_evaluation_criteria": "<p>erag</p>",
        "description_about": "<p>43trg</p>",
        "description_benefit": null,
        "description_verification": "<p>erg</p>",
        "description_contribution": null,
        "description_implementation": null,
        "description_legal": null,
        "description_funding": null,
        "description_tutorial": null,
        "measure_id": "e6"
      }
    },
    {
      "applicable": true,
      "rating": "0.6666",
      "localteam_id": "365577bb-31c6-46fb-8e42-9e3e53376cf0",
      "measure_id": "91f23d78-f610-4363-959a-1f1e99007367",
      "id": "5f57d7a6-b026-4f68-bf10-df892ce6b02d",
      "source": "sadf",
      "current_progress": "asdf",
      "date_updated": "2025-09-19T10:12:36.772Z",
      "why_not_applicable": null,
      "status": "published",
      "measure_published": true,
      "measure": {
        "id": "91f23d78-f610-4363-959a-1f1e99007367",
        "name": "ENergie 3",
        "sector": "energy",
        "slug": "energie-3",
        "impact": 5,
        "weight": 1,
        "feasibility_political": "1",
        "feasibility_economical": "5",
        "verification_description": null,
        "notes": null,
        "description": null,
        "date_updated": "2025-09-19T10:01:56.632Z",
        "description_evaluation_criteria": "<p>asdf</p>",
        "description_about": "<p>35</p>",
        "description_benefit": null,
        "description_verification": "<p>Land 2</p>",
        "description_contribution": null,
        "description_implementation": null,
        "description_legal": null,
        "description_funding": null,
        "description_tutorial": null,
        "measure_id": "en3"
      }
    },
    {
      "applicable": true,
      "rating": "0.1",
      "localteam_id": "365577bb-31c6-46fb-8e42-9e3e53376cf0",
      "measure_id": "9dcc2a5c-98e8-427c-841a-e3b540198a94",
      "id": "6c8bdf4d-cd25-4072-8ea1-9b091c3253a4",
      "source": "sadf",
      "current_progress": "asdf",
      "date_updated": "2025-09-19T10:12:36.799Z",
      "why_not_applicable": null,
      "status": "published",
      "measure_published": true,
      "measure": {
        "id": "9dcc2a5c-98e8-427c-841a-e3b540198a94",
        "name": "Energiemasbame",
        "sector": "energy",
        "slug": "energiemasbame",
        "impact": 2,
        "weight": 4,
        "feasibility_political": "2",
        "feasibility_economical": "1",
        "verification_description": null,
        "notes": null,
        "description": null,
        "date_updated": "2025-09-19T10:01:56.637Z",
        "description_evaluation_criteria": "<p>asdfasdf</p>",
        "description_about": "<p>asdf</p>",
        "description_benefit": null,
        "description_verification": "<p>asdfsdfsaf</p>",
        "description_contribution": null,
        "description_implementation": null,
        "description_legal": null,
        "description_funding": null,
        "description_tutorial": null,
        "measure_id": "EM3"
      }
    },
    {
      "applicable": true,
      "rating": "0.2",
      "localteam_id": "365577bb-31c6-46fb-8e42-9e3e53376cf0",
      "measure_id": "a671ebd5-9904-4cbd-89c1-f10cb8ba86ef",
      "id": "7e9495ac-8893-438a-8bce-d4b7bce0666e",
      "source": "sadf",
      "current_progress": "asdf",
      "date_updated": "2025-09-19T10:12:36.820Z",
      "why_not_applicable": null,
      "status": "published",
      "measure_published": true,
      "measure": {
        "id": "a671ebd5-9904-4cbd-89c1-f10cb8ba86ef",
        "name": "Nochmal Energie",
        "sector": "energy",
        "slug": "nochmal-energie",
        "impact": 2,
        "weight": 4,
        "feasibility_political": "2",
        "feasibility_economical": "1",
        "verification_description": null,
        "notes": null,
        "description": null,
        "date_updated": "2025-09-19T10:01:56.633Z",
        "description_evaluation_criteria": "<p>sdf</p>",
        "description_about": "<p>asdf</p>",
        "description_benefit": null,
        "description_verification": "<p>sdfdfa</p>",
        "description_contribution": null,
        "description_implementation": null,
        "description_legal": null,
        "description_funding": null,
        "description_tutorial": null,
        "measure_id": "EN4"
      }
    },
    {
      "applicable": true,
      "rating": "0",
      "localteam_id": "365577bb-31c6-46fb-8e42-9e3e53376cf0",
      "measure_id": "ce129e88-386c-429e-a0b0-9dca98dba5be",
      "id": "7ee6434d-1b22-4a5a-991b-15723c162039",
      "source": "sadf",
      "current_progress": "asdf",
      "date_updated": "2025-09-27T11:49:31.050Z",
      "why_not_applicable": null,
      "status": "published",
      "measure_published": true,
      "measure": {
        "id": "ce129e88-386c-429e-a0b0-9dca98dba5be",
        "name": "e5",
        "sector": "energy",
        "slug": "e5",
        "impact": 2,
        "weight": 1,
        "feasibility_political": "1",
        "feasibility_economical": "2",
        "verification_description": null,
        "notes": null,
        "description": null,
        "date_updated": "2025-09-19T10:01:56.628Z",
        "description_evaluation_criteria": "<p>ert</p>",
        "description_about": "<p>34</p>",
        "description_benefit": null,
        "description_verification": "<p>ewrt</p>",
        "description_contribution": null,
        "description_implementation": null,
        "description_legal": null,
        "description_funding": null,
        "description_tutorial": null,
        "measure_id": "e5"
      }
    },
    {
      "applicable": true,
      "rating": "0.4",
      "localteam_id": "365577bb-31c6-46fb-8e42-9e3e53376cf0",
      "measure_id": "d484438b-d8aa-41dc-b98e-6421b8f8067f",
      "id": "b630b744-ff02-4df6-a5de-b587f3c9b43f",
      "source": "sadf",
      "current_progress": "asdf",
      "date_updated": "2025-09-19T10:12:36.853Z",
      "why_not_applicable": null,
      "status": "published",
      "measure_published": true,
      "measure": {
        "id": "d484438b-d8aa-41dc-b98e-6421b8f8067f",
        "name": "e4",
        "sector": "energy",
        "slug": "e4",
        "impact": 3,
        "weight": 3,
        "feasibility_political": "2",
        "feasibility_economical": "2",
        "verification_description": null,
        "notes": null,
        "description": null,
        "date_updated": "2025-09-19T10:01:56.628Z",
        "description_evaluation_criteria": "<p>ert</p>",
        "description_about": "<p>ert</p>",
        "description_benefit": null,
        "description_verification": "<p>ewrt</p>",
        "description_contribution": null,
        "description_implementation": null,
        "description_legal": null,
        "description_funding": null,
        "description_tutorial": null,
        "measure_id": "e4"
      }
    },
    {
      "applicable": true,
      "rating": "1",
      "localteam_id": "365577bb-31c6-46fb-8e42-9e3e53376cf0",
      "measure_id": "d484438b-d8aa-41dc-b98e-6421b8f8067f",
      "id": "b630b744-ff02-4df6-a5de-b587f3c9b43f",
      "source": "sadf",
      "current_progress": "asdf",
      "date_updated": "2025-09-19T10:12:36.853Z",
      "why_not_applicable": null,
      "status": "published",
      "measure_published": true,
      "measure": {
        "id": "d484438b-d8aa-41dc-b98e-6421b8f8067f",
        "name": "e4",
        "sector": "energy",
        "slug": "e4",
        "impact": 3,
        "weight": 3,
        "feasibility_political": "2",
        "feasibility_economical": "2",
        "verification_description": null,
        "notes": null,
        "description": null,
        "date_updated": "2025-09-19T10:01:56.628Z",
        "description_evaluation_criteria": "<p>ert</p>",
        "description_about": "<p>ert</p>",
        "description_benefit": null,
        "description_verification": "<p>ewrt</p>",
        "description_contribution": null,
        "description_implementation": null,
        "description_legal": null,
        "description_funding": null,
        "description_tutorial": null,
        "measure_id": "e4"
      }
    },
    {
      "applicable": true,
      "rating": "0.9",
      "localteam_id": "365577bb-31c6-46fb-8e42-9e3e53376cf0",
      "measure_id": "d484438b-d8aa-41dc-b98e-6421b8f8067f",
      "id": "b630b744-ff02-4df6-a5de-b587f3c9b43f",
      "source": "sadf",
      "current_progress": "asdf",
      "date_updated": "2025-09-19T10:12:36.853Z",
      "why_not_applicable": null,
      "status": "published",
      "measure_published": true,
      "measure": {
        "id": "d484438b-d8aa-41dc-b98e-6421b8f8067f",
        "name": "e4",
        "sector": "energy",
        "slug": "e4",
        "impact": 3,
        "weight": 3,
        "feasibility_political": "2",
        "feasibility_economical": "2",
        "verification_description": null,
        "notes": null,
        "description": null,
        "date_updated": "2025-09-19T10:01:56.628Z",
        "description_evaluation_criteria": "<p>ert</p>",
        "description_about": "<p>ert</p>",
        "description_benefit": null,
        "description_verification": "<p>ewrt</p>",
        "description_contribution": null,
        "description_implementation": null,
        "description_legal": null,
        "description_funding": null,
        "description_tutorial": null,
        "measure_id": "e4"
      }
    },
    {
      "applicable": true,
      "rating": "0.8",
      "localteam_id": "365577bb-31c6-46fb-8e42-9e3e53376cf0",
      "measure_id": "d484438b-d8aa-41dc-b98e-6421b8f8067f",
      "id": "b630b744-ff02-4df6-a5de-b587f3c9b43f",
      "source": "sadf",
      "current_progress": "asdf",
      "date_updated": "2025-09-19T10:12:36.853Z",
      "why_not_applicable": null,
      "status": "published",
      "measure_published": true,
      "measure": {
        "id": "d484438b-d8aa-41dc-b98e-6421b8f8067f",
        "name": "e4",
        "sector": "energy",
        "slug": "e4",
        "impact": 3,
        "weight": 3,
        "feasibility_political": "2",
        "feasibility_economical": "2",
        "verification_description": null,
        "notes": null,
        "description": null,
        "date_updated": "2025-09-19T10:01:56.628Z",
        "description_evaluation_criteria": "<p>ert</p>",
        "description_about": "<p>ert</p>",
        "description_benefit": null,
        "description_verification": "<p>ewrt</p>",
        "description_contribution": null,
        "description_implementation": null,
        "description_legal": null,
        "description_funding": null,
        "description_tutorial": null,
        "measure_id": "e4"
      }
    },
    {
      "applicable": true,
      "rating": "0.7",
      "localteam_id": "365577bb-31c6-46fb-8e42-9e3e53376cf0",
      "measure_id": "d484438b-d8aa-41dc-b98e-6421b8f8067f",
      "id": "b630b744-ff02-4df6-a5de-b587f3c9b43f",
      "source": "sadf",
      "current_progress": "asdf",
      "date_updated": "2025-09-19T10:12:36.853Z",
      "why_not_applicable": null,
      "status": "published",
      "measure_published": true,
      "measure": {
        "id": "d484438b-d8aa-41dc-b98e-6421b8f8067f",
        "name": "e4",
        "sector": "energy",
        "slug": "e4",
        "impact": 3,
        "weight": 3,
        "feasibility_political": "2",
        "feasibility_economical": "2",
        "verification_description": null,
        "notes": null,
        "description": null,
        "date_updated": "2025-09-19T10:01:56.628Z",
        "description_evaluation_criteria": "<p>ert</p>",
        "description_about": "<p>ert</p>",
        "description_benefit": null,
        "description_verification": "<p>ewrt</p>",
        "description_contribution": null,
        "description_implementation": null,
        "description_legal": null,
        "description_funding": null,
        "description_tutorial": null,
        "measure_id": "e4"
      }
    }
  ],
  "ann": [
    {
      "applicable": true,
      "rating": "0.3333",
      "localteam_id": "365577bb-31c6-46fb-8e42-9e3e53376cf0",
      "measure_id": "022a7abf-7da1-4955-9194-3402aaf5f09c",
      "id": "30506b69-c8fb-4d7b-acee-cf132fff179d",
      "source": "sadf",
      "current_progress": "asdf",
      "date_updated": "2025-09-19T10:13:03.733Z",
      "why_not_applicable": null,
      "status": "published",
      "measure_published": true,
      "measure": {
        "id": "022a7abf-7da1-4955-9194-3402aaf5f09c",
        "name": "LN2",
        "sector": "ann",
        "slug": "ln2",
        "impact": 2,
        "weight": 3,
        "feasibility_political": "2",
        "feasibility_economical": "2",
        "verification_description": null,
        "notes": null,
        "description": null,
        "date_updated": "2025-09-19T10:01:56.542Z",
        "description_evaluation_criteria": "<p>adg</p>",
        "description_about": "<p>234adf</p>",
        "description_benefit": null,
        "description_verification": "<p>asdf</p>",
        "description_contribution": null,
        "description_implementation": null,
        "description_legal": null,
        "description_funding": null,
        "description_tutorial": null,
        "measure_id": "LNE 2"
      }
    },
    {
      "applicable": true,
      "rating": "0.6666",
      "localteam_id": "365577bb-31c6-46fb-8e42-9e3e53376cf0",
      "measure_id": "2f53f8ae-7f1e-4bda-bae7-148afea53f68",
      "id": "4aa87336-6080-42b0-af63-bf18f150466f",
      "source": "sadf",
      "current_progress": "asdf",
      "date_updated": "2025-09-19T10:12:36.721Z",
      "why_not_applicable": null,
      "status": "published",
      "measure_published": true,
      "measure": {
        "id": "2f53f8ae-7f1e-4bda-bae7-148afea53f68",
        "name": "Land 3",
        "sector": "ann",
        "slug": "land-3",
        "impact": 2,
        "weight": 3,
        "feasibility_political": "5",
        "feasibility_economical": "5",
        "verification_description": null,
        "notes": null,
        "description": null,
        "date_updated": "2025-09-19T10:01:56.547Z",
        "description_evaluation_criteria": "<p>adg</p>",
        "description_about": "<p>Land 2e</p>",
        "description_benefit": null,
        "description_verification": "<p>adg</p>",
        "description_contribution": null,
        "description_implementation": null,
        "description_legal": null,
        "description_funding": null,
        "description_tutorial": null,
        "measure_id": "ln3"
      }
    },
    {
      "applicable": true,
      "rating": "0.6666",
      "localteam_id": "365577bb-31c6-46fb-8e42-9e3e53376cf0",
      "measure_id": "93463e99-f8b1-4cfa-ab5e-5b348131fc58",
      "id": "4cab8868-af82-4197-9426-1acd9b34b5b8",
      "source": "sadf",
      "current_progress": "asdf",
      "date_updated": "2025-09-19T10:12:36.728Z",
      "why_not_applicable": null,
      "status": "published",
      "measure_published": true,
      "measure": {
        "id": "93463e99-f8b1-4cfa-ab5e-5b348131fc58",
        "name": "l5",
        "sector": "ann",
        "slug": "l5",
        "impact": 3,
        "weight": 2,
        "feasibility_political": "1",
        "feasibility_economical": "2",
        "verification_description": null,
        "notes": null,
        "description": null,
        "date_updated": "2025-09-19T10:01:56.545Z",
        "description_evaluation_criteria": "<p>asdf</p>",
        "description_about": "<p>asdf</p>",
        "description_benefit": null,
        "description_verification": "<p>asdf</p>",
        "description_contribution": null,
        "description_implementation": null,
        "description_legal": null,
        "description_funding": null,
        "description_tutorial": null,
        "measure_id": "l5"
      }
    },
    {
      "applicable": true,
      "rating": "0.6666",
      "localteam_id": "365577bb-31c6-46fb-8e42-9e3e53376cf0",
      "measure_id": "fae13b0a-fd92-4f2d-9422-1fc2c53c0c8e",
      "id": "4d663b65-6e91-476e-a4f3-505bb5d746e2",
      "source": "sadf",
      "current_progress": "asdf",
      "date_updated": "2025-09-19T10:12:36.735Z",
      "why_not_applicable": null,
      "status": "published",
      "measure_published": true,
      "measure": {
        "id": "fae13b0a-fd92-4f2d-9422-1fc2c53c0c8e",
        "name": "l6",
        "sector": "ann",
        "slug": "l6",
        "impact": 3,
        "weight": 3,
        "feasibility_political": "3",
        "feasibility_economical": "5",
        "verification_description": null,
        "notes": null,
        "description": null,
        "date_updated": "2025-09-19T10:01:56.543Z",
        "description_evaluation_criteria": "<p>asdf</p>",
        "description_about": "<p>dasf</p>",
        "description_benefit": null,
        "description_verification": "<p>dasas</p>",
        "description_contribution": null,
        "description_implementation": null,
        "description_legal": null,
        "description_funding": null,
        "description_tutorial": null,
        "measure_id": "l6"
      }
    },
    {
      "applicable": true,
      "rating": "0.6666",
      "localteam_id": "365577bb-31c6-46fb-8e42-9e3e53376cf0",
      "measure_id": "27a868b3-8a30-49bd-af71-08088550efd7",
      "id": "dafa5be5-d199-4b86-b7c8-91a8f3e1978e",
      "source": "sadf",
      "current_progress": "asdf",
      "date_updated": "2025-09-19T10:12:36.887Z",
      "why_not_applicable": null,
      "status": "published",
      "measure_published": true,
      "measure": {
        "id": "27a868b3-8a30-49bd-af71-08088550efd7",
        "name": "M51",
        "sector": "ann",
        "slug": "m51",
        "impact": 1,
        "weight": 1,
        "feasibility_political": "2",
        "feasibility_economical": "2",
        "verification_description": null,
        "notes": null,
        "description": null,
        "date_updated": "2025-09-19T10:01:56.546Z",
        "description_evaluation_criteria": "<p>sadf</p>",
        "description_about": "<p>asdf</p>",
        "description_benefit": null,
        "description_verification": "<p>asdf</p>",
        "description_contribution": null,
        "description_implementation": null,
        "description_legal": null,
        "description_funding": null,
        "description_tutorial": null,
        "measure_id": "EN_41"
      }
    },
    {
      "applicable": true,
      "rating": "0.6666",
      "localteam_id": "365577bb-31c6-46fb-8e42-9e3e53376cf0",
      "measure_id": "be300ac0-7496-4dc3-a9c0-c2294b4c5570",
      "id": "ff8ac47a-2ad5-4c73-8b6a-59e48c867024",
      "source": "sadf",
      "current_progress": "asdf",
      "date_updated": "2025-09-19T10:12:36.929Z",
      "why_not_applicable": null,
      "status": "published",
      "measure_published": true,
      "measure": {
        "id": "be300ac0-7496-4dc3-a9c0-c2294b4c5570",
        "name": "l3",
        "sector": "ann",
        "slug": "l3",
        "impact": 2,
        "weight": 3,
        "feasibility_political": "2",
        "feasibility_economical": "2",
        "verification_description": null,
        "notes": null,
        "description": null,
        "date_updated": "2025-09-19T10:01:56.546Z",
        "description_evaluation_criteria": "<p>asdf</p>",
        "description_about": "<p>34</p>",
        "description_benefit": null,
        "description_verification": "<p>asfd</p>",
        "description_contribution": null,
        "description_implementation": null,
        "description_legal": null,
        "description_funding": null,
        "description_tutorial": null,
        "measure_id": "l3"
      }
    }
  ],
  "iec": [
    {
      "applicable": true,
      "rating": "0.6666",
      "localteam_id": "365577bb-31c6-46fb-8e42-9e3e53376cf0",
      "measure_id": "18c3826b-5e76-44cb-933e-cf6a948c84a1",
      "id": "3e0beb5b-9acd-4efd-8f33-7bc2c190833d",
      "source": "sadf",
      "current_progress": "asdf",
      "date_updated": "2025-09-19T10:12:36.673Z",
      "why_not_applicable": null,
      "status": "published",
      "measure_published": true,
      "measure": {
        "id": "18c3826b-5e76-44cb-933e-cf6a948c84a1",
        "name": "g8",
        "sector": "iec",
        "slug": "g8",
        "impact": 3,
        "weight": 3,
        "feasibility_political": "2",
        "feasibility_economical": "2",
        "verification_description": null,
        "notes": null,
        "description": null,
        "date_updated": "2025-09-19T10:01:56.673Z",
        "description_evaluation_criteria": "<p>asfd</p>",
        "description_about": "<p>asdf</p>",
        "description_benefit": null,
        "description_verification": "<p>asfd</p>",
        "description_contribution": null,
        "description_implementation": null,
        "description_legal": null,
        "description_funding": null,
        "description_tutorial": null,
        "measure_id": "g8"
      }
    },
    {
      "applicable": true,
      "rating": "0.6666",
      "localteam_id": "365577bb-31c6-46fb-8e42-9e3e53376cf0",
      "measure_id": "fbca1e3e-53b7-495d-beb3-0e8768f3a364",
      "id": "43d94b9a-7bc0-4186-9d18-b1935b0f1641",
      "source": "sadf",
      "current_progress": "asdf",
      "date_updated": "2025-09-19T10:12:36.695Z",
      "why_not_applicable": null,
      "status": "published",
      "measure_published": true,
      "measure": {
        "id": "fbca1e3e-53b7-495d-beb3-0e8768f3a364",
        "name": "Indu3",
        "sector": "iec",
        "slug": "indu3",
        "impact": 1,
        "weight": 1,
        "feasibility_political": "1",
        "feasibility_economical": "1",
        "verification_description": null,
        "notes": null,
        "description": null,
        "date_updated": "2025-09-19T10:01:56.674Z",
        "description_evaluation_criteria": "<p>wer</p>",
        "description_about": "<p>wer</p>",
        "description_benefit": null,
        "description_verification": "<p>wer</p>",
        "description_contribution": null,
        "description_implementation": null,
        "description_legal": null,
        "description_funding": null,
        "description_tutorial": null,
        "measure_id": "in3"
      }
    },
    {
      "applicable": true,
      "rating": "0.6666",
      "localteam_id": "365577bb-31c6-46fb-8e42-9e3e53376cf0",
      "measure_id": "408a8182-1ac7-44cc-b958-5d7bec796de1",
      "id": "6128ca27-fd3d-4f70-8874-8797bfe715ca",
      "source": "sadf",
      "current_progress": "asdf",
      "date_updated": "2025-09-19T10:12:36.778Z",
      "why_not_applicable": null,
      "status": "published",
      "measure_published": true,
      "measure": {
        "id": "408a8182-1ac7-44cc-b958-5d7bec796de1",
        "name": "in5",
        "sector": "iec",
        "slug": "in5",
        "impact": 2,
        "weight": 2,
        "feasibility_political": "2",
        "feasibility_economical": "2",
        "verification_description": null,
        "notes": null,
        "description": null,
        "date_updated": "2025-09-19T10:01:56.666Z",
        "description_evaluation_criteria": "<p>Land 2</p>",
        "description_about": "<p>qrwerLand 2</p>",
        "description_benefit": null,
        "description_verification": "<p>Land 2</p>",
        "description_contribution": null,
        "description_implementation": null,
        "description_legal": null,
        "description_funding": null,
        "description_tutorial": null,
        "measure_id": "in5"
      }
    },
    {
      "applicable": true,
      "rating": "0.6666",
      "localteam_id": "365577bb-31c6-46fb-8e42-9e3e53376cf0",
      "measure_id": "45302e55-70ee-46f5-b6d0-db448262aeee",
      "id": "8aa94fd1-d454-4507-b345-55b4e953140d",
      "source": "sadf",
      "current_progress": "asdf",
      "date_updated": "2025-09-19T10:12:36.832Z",
      "why_not_applicable": null,
      "status": "published",
      "measure_published": true,
      "measure": {
        "id": "45302e55-70ee-46f5-b6d0-db448262aeee",
        "name": "industire 1",
        "sector": "iec",
        "slug": "industire-1",
        "impact": 2,
        "weight": 1,
        "feasibility_political": "3",
        "feasibility_economical": "2",
        "verification_description": null,
        "notes": null,
        "description": null,
        "date_updated": "2025-09-19T10:01:56.673Z",
        "description_evaluation_criteria": "<p>sadf</p>",
        "description_about": "<p>er</p>",
        "description_benefit": null,
        "description_verification": "<p>asdf</p>",
        "description_contribution": null,
        "description_implementation": null,
        "description_legal": null,
        "description_funding": null,
        "description_tutorial": null,
        "measure_id": "industire 1"
      }
    },
    {
      "applicable": true,
      "rating": "0",
      "localteam_id": "365577bb-31c6-46fb-8e42-9e3e53376cf0",
      "measure_id": "684b3418-c44f-4e1a-b4a5-3dff83ef24ad",
      "id": "bc013520-371d-42a5-974d-11fe2dc3ff6b",
      "source": "sadf",
      "current_progress": "asdf",
      "date_updated": "2025-09-27T11:49:41.335Z",
      "why_not_applicable": null,
      "status": "published",
      "measure_published": true,
      "measure": {
        "id": "684b3418-c44f-4e1a-b4a5-3dff83ef24ad",
        "name": "in6",
        "sector": "iec",
        "slug": "in6",
        "impact": 4,
        "weight": 2,
        "feasibility_political": "2",
        "feasibility_economical": "2",
        "verification_description": null,
        "notes": null,
        "description": null,
        "date_updated": "2025-09-19T10:01:56.678Z",
        "description_evaluation_criteria": "<p>erht</p>",
        "description_about": "<p>rth</p>",
        "description_benefit": null,
        "description_verification": "<p>rth</p>",
        "description_contribution": null,
        "description_implementation": null,
        "description_legal": null,
        "description_funding": null,
        "description_tutorial": null,
        "measure_id": "in6"
      }
    },
    {
      "applicable": true,
      "rating": "0.6666",
      "localteam_id": "365577bb-31c6-46fb-8e42-9e3e53376cf0",
      "measure_id": "7e0acd44-66aa-4fa5-97c6-6b7cd34be831",
      "id": "d2e57f1a-28eb-4012-9683-34ed7a6a87cb",
      "source": "sadf",
      "current_progress": "asdf",
      "date_updated": "2025-09-19T10:12:36.879Z",
      "why_not_applicable": null,
      "status": "published",
      "measure_published": true,
      "measure": {
        "id": "7e0acd44-66aa-4fa5-97c6-6b7cd34be831",
        "name": "indu4",
        "sector": "iec",
        "slug": "indu4",
        "impact": 2,
        "weight": 5,
        "feasibility_political": "3",
        "feasibility_economical": "3",
        "verification_description": null,
        "notes": null,
        "description": null,
        "date_updated": "2025-09-19T10:01:56.672Z",
        "description_evaluation_criteria": "<p>sdf</p>",
        "description_about": "<p>eqr</p>",
        "description_benefit": null,
        "description_verification": "<p>reqt</p>",
        "description_contribution": null,
        "description_implementation": null,
        "description_legal": null,
        "description_funding": null,
        "description_tutorial": null,
        "measure_id": "in4"
      }
    },
    {
      "applicable": true,
      "rating": "0.6666",
      "localteam_id": "365577bb-31c6-46fb-8e42-9e3e53376cf0",
      "measure_id": "eae0d9fa-8e6a-4d6a-ad4d-94347d6c8b86",
      "id": "e2ce4efd-3c31-4845-a663-2b40a98817f4",
      "source": "sadf",
      "current_progress": "asdf",
      "date_updated": "2025-09-19T10:12:36.922Z",
      "why_not_applicable": null,
      "status": "published",
      "measure_published": true,
      "measure": {
        "id": "eae0d9fa-8e6a-4d6a-ad4d-94347d6c8b86",
        "name": "Industrie 1",
        "sector": "iec",
        "slug": "industrie-1",
        "impact": 2,
        "weight": 2,
        "feasibility_political": "4",
        "feasibility_economical": "4",
        "verification_description": null,
        "notes": null,
        "description": null,
        "date_updated": "2025-09-19T10:01:56.677Z",
        "description_evaluation_criteria": "<p>agfd</p>",
        "description_about": "<p>qwergf</p>",
        "description_benefit": null,
        "description_verification": "<p>adgf</p>",
        "description_contribution": null,
        "description_implementation": null,
        "description_legal": null,
        "description_funding": null,
        "description_tutorial": null,
        "measure_id": "in2"
      }
    }
  ]
}